antspymm/__init__.py
antspymm/mm.py
antspymm-1.6.4.dist-info/METADATA
antspymm-1.6.4.dist-info/WHEEL
antspymm-1.6.4.dist-info/top_level.txt
antspymm-1.6.4.dist-info/RECORD
