Metadata-Version: 2.4
Name: antspymm
Version: 1.6.4
Summary: multi-channel/time-series medical image processing with antspyx
Author-email: "Avants, Gosselin, Tustison, Reardon" <stnava@gmail.com>
License: Apache-2.0
Classifier: License :: OSI Approved :: Apache Software License
Classifier: Programming Language :: Python :: 3
Classifier: Operating System :: OS Independent
Requires-Python: >=3.9
Requires-Dist: h5py>=2.10.0
Requires-Dist: numpy>=1.19.4
Requires-Dist: pandas>=1.0.1
Requires-Dist: antspyx>=0.4.2
Requires-Dist: antspynet>=0.3.0
Requires-Dist: antspyt1w>=1.1.0
Requires-Dist: pathlib
Requires-Dist: dipy
Requires-Dist: nibabel
Requires-Dist: scipy
Requires-Dist: siq
Requires-Dist: scikit-learn
